README.md
setup.py
my_library/__init__.py
my_library/module1.py
my_library/module2.py
praveengcs_test_my_library.egg-info/PKG-INFO
praveengcs_test_my_library.egg-info/SOURCES.txt
praveengcs_test_my_library.egg-info/dependency_links.txt
praveengcs_test_my_library.egg-info/top_level.txt