Metadata-Version: 2.1
Name: praveengcs-test-my-library
Version: 0.1
Summary: A brief description of your library
Home-page: https://github.com/your_username/my_library
Author: Praveen
Author-email: your_email@example.com
License: UNKNOWN
Platform: UNKNOWN
Classifier: Programming Language :: Python :: 3
Classifier: License :: OSI Approved :: MIT License
Classifier: Operating System :: OS Independent
Requires-Python: >=3.8
